LICENSE
MANIFEST.in
README.rst
VERSION
requirements.txt
setup.py
grano/__init__.py
grano/authz.py
grano/background.py
grano/constants.py
grano/core.py
grano/default_settings.py
grano/interface.py
grano/logs.py
grano/manage.py
grano/plugins.py
grano/providers.py
grano.egg-info/PKG-INFO
grano.egg-info/SOURCES.txt
grano.egg-info/dependency_links.txt
grano.egg-info/entry_points.txt
grano.egg-info/namespace_packages.txt
grano.egg-info/not-zip-safe
grano.egg-info/requires.txt
grano.egg-info/top_level.txt
grano/alembic/alembic.ini
grano/alembic/env.py
grano/alembic/script.py.mako
grano/alembic/versions/1b1b7e728dc4_single_schema_entity.py
grano/alembic/versions/2372546f7078_pipeline_model_improved.py
grano/alembic/versions/25bb7c68b5fa_add_file_foreign_key_to_property.py
grano/alembic/versions/2b269c4557de_introduce_private_project_and_roles.py
grano/alembic/versions/2b65d3dfa1de_foreign_keys_for_project.py
grano/alembic/versions/32a25698e4bb_pipeline_models.py
grano/alembic/versions/383da0877c75_add_status_field_to_entity.py
grano/alembic/versions/38c7982f4160_add_degree_denormalizations.py
grano/alembic/versions/3a3c75de71b_.py
grano/alembic/versions/3c486a5dcceb_transform_the_account.py
grano/alembic/versions/3f0a4c96f763_add_schema_inheritance.py
grano/alembic/versions/40941ab93ba_introduce_project_class.py
grano/alembic/versions/48dd6f2e0784_.py
grano/alembic/versions/4d7168864daa_log_entry_models.py
grano/alembic/versions/4f21a77e91be_init.py
grano/alembic/versions/4fb92f3ede9e_.py
grano/alembic/versions/5143617349b9_simplify_property_model.py
grano/alembic/versions/52f4346513a8_add_file_relation.py
grano/alembic/versions/59d7b4f94cdf_remove_status_again.py
grano/alembic/versions/5a34d3b6a160_.py
grano/alembic/versions/992aea84727_.py
grano/alembic/versions/b64496669cd_add_value_datetime_precision_to_property.py
grano/alembic/versions/d7067cd4169_.py
grano/fixtures/base.yaml
grano/lib/__init__.py
grano/lib/args.py
grano/lib/data.py
grano/lib/exc.py
grano/lib/serialisation.py
grano/logic/__init__.py
grano/logic/accounts.py
grano/logic/aliases.py
grano/logic/attributes.py
grano/logic/entities.py
grano/logic/files.py
grano/logic/imports.py
grano/logic/loader.py
grano/logic/metrics.py
