Metadata-Version: 1.1
Name: grano
Version: 0.4.8
Summary: An investigative toolkit for influence influence mapping
Home-page: http://github.com/ANCIR/grano
Author: Code for Africa / ANCIR
Author-email: support@codeforafrica.org
License: MIT
Keywords: sql graph sna networks journalism ddj entities
Platform: UNKNOWN
Classifier: Development Status :: 3 - Alpha
Classifier: Intended Audience :: Developers
Classifier: Operating System :: OS Independent
Classifier: Programming Language :: Python
